linearpy/__init__.py
linearpy/exceptions.py
linearpy/linearpy.py
linearmath-0.1.0.dist-info/AUTHORS.rst
linearmath-0.1.0.dist-info/LICENSE
linearmath-0.1.0.dist-info/METADATA
linearmath-0.1.0.dist-info/WHEEL
linearmath-0.1.0.dist-info/top_level.txt
linearmath-0.1.0.dist-info/RECORD
