Metadata-Version: 2.1
Name: linearmath
Version: 0.1.0
Summary: The python toolkit for Linear Algebra.
Author-email: Ahmed abdulellah Haidar Shayea <solomonsh@gmail.com>
Maintainer-email: Ahmed abdulellah Haidar Shayea <solomonsh@gmail.com>
License: GNU General Public License v3
Project-URL: bugs, https://github.com/shayea-colla/linearpy/issues
Project-URL: changelog, https://github.com/shayea-colla/linearpy/blob/master/changelog.md
Project-URL: homepage, https://github.com/shayea-colla/linearpy
License-File: LICENSE
License-File: AUTHORS.rst
Provides-Extra: dev
Requires-Dist: coverage ; extra == 'dev'
Requires-Dist: mypy ; extra == 'dev'
Requires-Dist: pytest ; extra == 'dev'
Requires-Dist: ruff ; extra == 'dev'
